is_safe_url.py
is_safe_url-1.0.dist-info/LICENSE
is_safe_url-1.0.dist-info/METADATA
is_safe_url-1.0.dist-info/WHEEL
is_safe_url-1.0.dist-info/top_level.txt
is_safe_url-1.0.dist-info/RECORD
