Metadata-Version: 2.1
Name: is_safe_url
Version: 1.0
Summary: Django's is_safe_url() bundled as a standalone package.
Home-page: https://gitlab.com/MarkusH/is_safe_url
Author: Markus Holtermann, Django Software Foundation and individual contributors
Author-email: info@markusholtermann.eu
License: BSD
Platform: UNKNOWN
Classifier: License :: OSI Approved :: BSD License
Classifier: Programming Language :: Python
Classifier: Programming Language :: Python :: 2
Classifier: Programming Language :: Python :: 2.7
Classifier: Programming Language :: Python :: 3
Classifier: Programming Language :: Python :: 3.4
Classifier: Programming Language :: Python :: 3.5
Classifier: Programming Language :: Python :: 3.6
Classifier: Programming Language :: Python :: 3.7
